{
  "tests": [
    {
      "name": "test1",
      "setup": "cd exercise; make",
      "run": "./exercise/hanoi",
      "input": "3",
      "output": "[\\s\\S]*a[\\s\\S]*c[\\s\\S]*a[\\s\\S]*b[\\s\\S]*c[\\s\\S]*b[\\s\\S]*a[\\s\\S]*c[\\s\\S]*b[\\s\\S]*a[\\s\\S]*b[\\s\\S]*c[\\s\\S]*a[\\s\\S]*c",
      "comparison": "regex",
      "timeout": 1,
      "points": 10
    },
    {
      "name": "test2",
      "setup": "cd exercise; make",
      "run": "./exercise/hanoi",
      "input": "5",
      "output": "[\\s\\S]*a[\\s\\S]*c[\\s\\S]*a[\\s\\S]*b[\\s\\S]*c[\\s\\S]*b[\\s\\S]*a[\\s\\S]*c[\\s\\S]*b[\\s\\S]*a[\\s\\S]*b[\\s\\S]*c[\\s\\S]*a[\\s\\S]*c[\\s\\S]*a[\\s\\S]*b[\\s\\S]*c[\\s\\S]*b",
      "comparison": "regex",
      "timeout": 1,
      "points": 10
    },
    {
      "name": "test3",
      "setup": "cd exercise; make",
      "run": "./exercise/hanoi",
      "input": "13",
      "output": "[\\s\\S]*b[\\s\\S]*a[\\s\\S]*b[\\s\\S]*c[\\s\\S]*a[\\s\\S]*c[\\s\\S]*b[\\s\\S]*a[\\s\\S]*c[\\s\\S]*b[\\s\\S]*c[\\s\\S]*a",
      "comparison": "regex",
      "timeout": 1,
      "points": 10
    }
  ]
}